dxtrx/__init__.py
dxtrx/dagster/__init__.py
dxtrx/dagster/resources/__init__.py
dxtrx/dagster/resources/bigquery.py
dxtrx/dagster/resources/duckdb.py
dxtrx/dagster/resources/mlflow.py
dxtrx/dagster/resources/sharepoint.py
dxtrx/dagster/resources/sql.py
dxtrx/dagster/resources/sqlalchemy.py
dxtrx/dagster/resources/storage.py
dxtrx/utils/__init__.py
dxtrx/utils/dataframe.py
dxtrx/utils/dataframe_conversion.py
dxtrx/utils/hash.py
dxtrx/utils/jinja.py
dxtrx/utils/json.py
dxtrx/utils/logging.py
dxtrx/utils/pandas.py
dxtrx/utils/papermill.py
dxtrx/utils/sql.py
dxtrx/utils/string.py
dxtrx/utils/types.py
dxtrx/utils/cache/__init__.py
dxtrx/utils/cache/gcs.py
dxtrx/utils/ml/__init__.py
dxtrx/utils/ml/load.py
dxtrx/utils/ml/llm/__init__.py
dxtrx/utils/ml/llm/domain.py
dxtrx/utils/ml/llm/limiter.py
dxtrx/utils/ml/llm/prompt.py
dxtrx/utils/ml/llm/schema_mapper.py
dxtrx/utils/ml/text/__init__.py
dxtrx/utils/ml/text/fasttext.py
dxtrx-0.0.8.dist-info/licenses/LICENSE
dxtrx-0.0.8.dist-info/METADATA
dxtrx-0.0.8.dist-info/WHEEL
dxtrx-0.0.8.dist-info/top_level.txt
dxtrx-0.0.8.dist-info/RECORD
