Metadata-Version: 2.4
Name: dxtrx
Version: 0.0.8
Summary: Dagster extra utilities for data processing
License: MIT
Requires-Python: >=3.11.8
License-File: LICENSE
Requires-Dist: polars>=0.20.0
Requires-Dist: google-cloud-storage>=1.0.0
Requires-Dist: requests>=2.0.0
Requires-Dist: msal>=1.0.0
Requires-Dist: pyyaml>=5.0.0
Requires-Dist: pandas>=1.0.0
Requires-Dist: python-dotenv>=0.19.0
Requires-Dist: pyarrow>=10.0.0
Requires-Dist: sqlalchemy>=1.4.0
Requires-Dist: psycopg2-binary>=2.8.0
Requires-Dist: duckdb-engine>=0.9.0
Requires-Dist: fastexcel>=0.10.0
Requires-Dist: orjson>=3.0.0
Requires-Dist: sqlglot>=20.0.0
Requires-Dist: aiohttp>=3.8.0
Requires-Dist: openpyxl>=3.0.0
Requires-Dist: fsspec>=2022.1.0
Requires-Dist: gcsfs>=2022.1.0
Provides-Extra: dev
Requires-Dist: pytest; extra == "dev"
Requires-Dist: pytest-mock; extra == "dev"
Requires-Dist: pytest-cov; extra == "dev"
Requires-Dist: pytest-asyncio; extra == "dev"
Requires-Dist: pytest-watch; extra == "dev"
Dynamic: license-file
